pandas_little_helper/_version.py
pandas_little_helper/helpers.py
pandas_little_helper/transformers.py
pandas_little_helper-0.1a0.dist-info/LICENSE.txt
pandas_little_helper-0.1a0.dist-info/METADATA
pandas_little_helper-0.1a0.dist-info/WHEEL
pandas_little_helper-0.1a0.dist-info/top_level.txt
pandas_little_helper-0.1a0.dist-info/RECORD
