Metadata-Version: 2.1
Name: pandas-little-helper
Version: 0.1a0
Summary: List of helpful data science stuff
Home-page: https://github.com/guruyaya/pandas_little_helper
Author: Yair Eshel Cahansky
Author-email: guruyaya@gmail.com
License: UNKNOWN
Platform: UNKNOWN
Classifier: Programming Language :: Python :: 3
Classifier: License :: OSI Approved :: GNU General Public License v3 (GPLv3)
Classifier: Operating System :: OS Independent
